meemoo_sip_validator/__init__.py
meemoo_sip_validator/_cli/validator.py
meemoo_sip_validator/assets/edtf.xsd.xml
meemoo_sip_validator/assets/mets-1-12.xsd.xml
meemoo_sip_validator/assets/premis-3-0.xsd.xml
meemoo_sip_validator/assets/xlink-2.xsd.xml
meemoo_sip_validator/assets/xml.xsd.xml
meemoo_sip_validator/assets/2.1/basic-2-1.xsd.xml
meemoo_sip_validator/assets/2.1/basic-dcterms-2-1.xsd.xml
meemoo_sip_validator/assets/2.1/basic-schema-2-1.xsd.xml
meemoo_sip_validator/assets/2.1/film-2-1.xsd.xml
meemoo_sip_validator/assets/2.1/material-artwork-2-1.xsd.xml
meemoo_sip_validator/v2_1/__init__.py
meemoo_sip_validator/v2_1/_core/codes.py
meemoo_sip_validator/v2_1/_core/commons_ip.py
meemoo_sip_validator/v2_1/_core/models.py
meemoo_sip_validator/v2_1/_core/profiles.py
meemoo_sip_validator/v2_1/_core/report.py
meemoo_sip_validator/v2_1/_core/structural.py
meemoo_sip_validator/v2_1/_core/thesauri.py
meemoo_sip_validator/v2_1/_core/utils.py
meemoo_sip_validator/v2_1/_core/validate.py
meemoo_sip_validator/v2_1/_core/xsd.py
meemoo_sip_validator/v2_1/_core/descriptive/dc_schema.py
meemoo_sip_validator/v2_1/_core/premis/helpers.py
meemoo_sip_validator/v2_1/_core/premis/premis.py
meemoo_sip_validator-0.2.9.dist-info/METADATA
meemoo_sip_validator-0.2.9.dist-info/WHEEL
meemoo_sip_validator-0.2.9.dist-info/entry_points.txt
meemoo_sip_validator-0.2.9.dist-info/top_level.txt
meemoo_sip_validator-0.2.9.dist-info/RECORD
