Metadata-Version: 2.4
Name: meemoo-sip-validator
Version: 0.2.9
Summary: A library to validate meemoo SIP's
Classifier: Programming Language :: Python :: 3.11
Requires-Python: >=3.11
Requires-Dist: py-commons-ip==0.3.2
Requires-Dist: xmlschema==4.1.0
Requires-Dist: edtf-validate==2.0.0
Requires-Dist: sipin-eark-models==0.0.12
Provides-Extra: dev
Requires-Dist: pytest==8.4.1; extra == "dev"
Requires-Dist: ruff==0.12.7; extra == "dev"
Requires-Dist: build==1.3.0; extra == "dev"
Requires-Dist: twine==6.1.0; extra == "dev"
